simian/__init__.py
simian/background.py
simian/batch.py
simian/camera.py
simian/combiner.py
simian/distributed.py
simian/object.py
simian/postprocessing.py
simian/render.py
simian/scene.py
simian/transform.py
simian/worker.py
simian3d-0.0.14.dist-info/METADATA
simian3d-0.0.14.dist-info/WHEEL
simian3d-0.0.14.dist-info/top_level.txt
simian3d-0.0.14.dist-info/RECORD
