Metadata-Version: 2.1
Name: simian3d
Version: 0.0.14
Summary: A synthetic data generator for video caption pairs.
Home-page: https://github.com/RaccoonResearch/Simian
Author: Raccoon Research
Author-email: shawmakesmagic@gmail.com
License: MIT
Classifier: Development Status :: 4 - Beta
Classifier: Intended Audience :: Science/Research
Classifier: License :: OSI Approved :: MIT License
Classifier: Operating System :: POSIX :: Linux
Classifier: Programming Language :: Python :: 3
Classifier: Operating System :: MacOS :: MacOS X
Classifier: Operating System :: Microsoft :: Windows
Requires-Dist: omegaconf
Requires-Dist: requests
Requires-Dist: argparse
Requires-Dist: numpy
Requires-Dist: scipy
Requires-Dist: distributaur
Requires-Dist: bpy
Requires-Dist: rr-infinigen
